[
  {
    "day": 1,
    "S_t": 2284,
    "Mbar_t": 2284,
    "M_t": "51999.9999999999995",
    "G_t": 0,
    "alpha_t": 0,
    "Mpeak_t": 2284,
    "gross_settled_t": 2284,
    "v_t": 1,
    "phi_t": 1,
    "delta_t": 0,
    "n_debtors": 1,
    "n_creditors": 2,
    "HHIplus_t": "0.6580184700697151585230078426",
    "notes": ""
  },
  {
    "day": 3,
    "S_t": 1908,
    "Mbar_t": 1908,
    "M_t": "51999.9999999999995",
    "G_t": 0,
    "alpha_t": 0,
    "Mpeak_t": 1908,
    "gross_settled_t": 1908,
    "v_t": 1,
    "phi_t": 1,
    "delta_t": 0,
    "n_debtors": 1,
    "n_creditors": 2,
    "HHIplus_t": "0.6132361149567747408022713588",
    "notes": ""
  },
  {
    "day": 5,
    "S_t": 7703,
    "Mbar_t": 7703,
    "M_t": "51999.9999999999995",
    "G_t": 0,
    "alpha_t": 0,
    "Mpeak_t": 7703,
    "gross_settled_t": 7703,
    "v_t": 1,
    "phi_t": 1,
    "delta_t": 0,
    "n_debtors": 1,
    "n_creditors": 2,
    "HHIplus_t": "0.8786070070637643871046766738",
    "notes": ""
  },
  {
    "day": 7,
    "S_t": 1525,
    "Mbar_t": 1525,
    "M_t": "51999.9999999999995",
    "G_t": 0,
    "alpha_t": 0,
    "Mpeak_t": 1525,
    "gross_settled_t": 1525,
    "v_t": 1,
    "phi_t": 1,
    "delta_t": 0,
    "n_debtors": 1,
    "n_creditors": 2,
    "HHIplus_t": "0.5592582639075517334049986562",
    "notes": ""
  },
  {
    "day": 9,
    "S_t": 1578,
    "Mbar_t": 1578,
    "M_t": "51999.9999999999995",
    "G_t": 0,
    "alpha_t": 0,
    "Mpeak_t": 1578,
    "gross_settled_t": 1578,
    "v_t": 1,
    "phi_t": 1,
    "delta_t": 0,
    "n_debtors": 1,
    "n_creditors": 2,
    "HHIplus_t": "0.5670828775254168132480671334",
    "notes": ""
  }
]