[
  {
    "day": 1,
    "S_t": 1130,
    "Mbar_t": 1130,
    "M_t": 10000,
    "G_t": 0,
    "alpha_t": 0,
    "Mpeak_t": 307,
    "gross_settled_t": 307,
    "v_t": 1,
    "phi_t": "0.2716814159292035398230088496",
    "delta_t": "0.7283185840707964601769911504",
    "n_debtors": 10,
    "n_creditors": 10,
    "HHIplus_t": "0.1129391495027018560576395959",
    "notes": ""
  },
  {
    "day": 2,
    "S_t": 1119,
    "Mbar_t": 1119,
    "M_t": 10000,
    "G_t": 0,
    "alpha_t": 0,
    "Mpeak_t": 308,
    "gross_settled_t": 308,
    "v_t": 1,
    "phi_t": "0.275245755138516532618409294",
    "delta_t": "0.724754244861483467381590706",
    "n_debtors": 10,
    "n_creditors": 10,
    "HHIplus_t": "0.1111079166337236186081502299",
    "notes": ""
  },
  {
    "day": 3,
    "S_t": 1037,
    "Mbar_t": 1037,
    "M_t": 10000,
    "G_t": 0,
    "alpha_t": 0,
    "Mpeak_t": 354,
    "gross_settled_t": 354,
    "v_t": 1,
    "phi_t": "0.3413693346190935390549662488",
    "delta_t": "0.6586306653809064609450337512",
    "n_debtors": 10,
    "n_creditors": 10,
    "HHIplus_t": "0.1143486561357078361009104781",
    "notes": ""
  },
  {
    "day": 4,
    "S_t": 886,
    "Mbar_t": 886,
    "M_t": 10000,
    "G_t": 0,
    "alpha_t": 0,
    "Mpeak_t": 413,
    "gross_settled_t": 413,
    "v_t": 1,
    "phi_t": "0.46613995485327313769751693",
    "delta_t": "0.53386004514672686230248307",
    "n_debtors": 10,
    "n_creditors": 10,
    "HHIplus_t": "0.1145050420639086059037243502",
    "notes": ""
  },
  {
    "day": 5,
    "S_t": 996,
    "Mbar_t": 996,
    "M_t": 10000,
    "G_t": 0,
    "alpha_t": 0,
    "Mpeak_t": 455,
    "gross_settled_t": 455,
    "v_t": 1,
    "phi_t": "0.4568273092369477911646586345",
    "delta_t": "0.5431726907630522088353413655",
    "n_debtors": 10,
    "n_creditors": 10,
    "HHIplus_t": "0.1145727488266318285188948566",
    "notes": ""
  },
  {
    "day": 6,
    "S_t": 1055,
    "Mbar_t": 1055,
    "M_t": 10000,
    "G_t": 0,
    "alpha_t": 0,
    "Mpeak_t": 381,
    "gross_settled_t": 381,
    "v_t": 1,
    "phi_t": "0.3611374407582938388625592417",
    "delta_t": "0.6388625592417061611374407583",
    "n_debtors": 10,
    "n_creditors": 10,
    "HHIplus_t": "0.1133945778396711664158487006",
    "notes": ""
  },
  {
    "day": 7,
    "S_t": 958,
    "Mbar_t": 958,
    "M_t": 10000,
    "G_t": 0,
    "alpha_t": 0,
    "Mpeak_t": 564,
    "gross_settled_t": 564,
    "v_t": 1,
    "phi_t": "0.5887265135699373695198329854",
    "delta_t": "0.4112734864300626304801670146",
    "n_debtors": 10,
    "n_creditors": 10,
    "HHIplus_t": "0.1074633565927624095083267594",
    "notes": ""
  },
  {
    "day": 8,
    "S_t": 1006,
    "Mbar_t": 1006,
    "M_t": 10000,
    "G_t": 0,
    "alpha_t": 0,
    "Mpeak_t": 166,
    "gross_settled_t": 166,
    "v_t": 1,
    "phi_t": "0.165009940357852882703777336",
    "delta_t": "0.834990059642147117296222664",
    "n_debtors": 10,
    "n_creditors": 10,
    "HHIplus_t": "0.1272583188740321490539862219",
    "notes": ""
  },
  {
    "day": 9,
    "S_t": 736,
    "Mbar_t": 736,
    "M_t": 10000,
    "G_t": 0,
    "alpha_t": 0,
    "Mpeak_t": 582,
    "gross_settled_t": 582,
    "v_t": 1,
    "phi_t": "0.7907608695652173913043478261",
    "delta_t": "0.2092391304347826086956521739",
    "n_debtors": 10,
    "n_creditors": 10,
    "HHIplus_t": "0.1196464437618147448015122873",
    "notes": ""
  },
  {
    "day": 10,
    "S_t": 1023,
    "Mbar_t": 1023,
    "M_t": 10000,
    "G_t": 0,
    "alpha_t": 0,
    "Mpeak_t": 1023,
    "gross_settled_t": 1023,
    "v_t": 1,
    "phi_t": 1,
    "delta_t": 0,
    "n_debtors": 10,
    "n_creditors": 10,
    "HHIplus_t": "0.1154626388757502181019350634",
    "notes": ""
  }
]