[
  {
    "day": 1,
    "S_t": 532,
    "Mbar_t": 532,
    "M_t": 5000,
    "G_t": 0,
    "alpha_t": 0,
    "Mpeak_t": 532,
    "gross_settled_t": 532,
    "v_t": 1,
    "phi_t": 1,
    "delta_t": 0,
    "n_debtors": 1,
    "n_creditors": 2,
    "HHIplus_t": "0.8869353835717112329696421506",
    "notes": ""
  },
  {
    "day": 3,
    "S_t": 1453,
    "Mbar_t": 1453,
    "M_t": 5000,
    "G_t": 0,
    "alpha_t": 0,
    "Mpeak_t": 0,
    "gross_settled_t": 0,
    "v_t": null,
    "phi_t": 0,
    "delta_t": 1,
    "n_debtors": 1,
    "n_creditors": 2,
    "HHIplus_t": "0.5485998780793374791410987732",
    "notes": ""
  },
  {
    "day": 5,
    "S_t": 10695,
    "Mbar_t": 10695,
    "M_t": 5000,
    "G_t": 5695,
    "alpha_t": 0,
    "Mpeak_t": 0,
    "gross_settled_t": 0,
    "v_t": null,
    "phi_t": 0,
    "delta_t": 1,
    "n_debtors": 1,
    "n_creditors": 2,
    "HHIplus_t": "0.9108696417147561886914601184",
    "notes": ""
  },
  {
    "day": 7,
    "S_t": 1154,
    "Mbar_t": 1154,
    "M_t": 5000,
    "G_t": 0,
    "alpha_t": 0,
    "Mpeak_t": 0,
    "gross_settled_t": 0,
    "v_t": null,
    "phi_t": 0,
    "delta_t": 1,
    "n_debtors": 1,
    "n_creditors": 2,
    "HHIplus_t": "0.5089043009170123359635237544",
    "notes": ""
  },
  {
    "day": 9,
    "S_t": 1164,
    "Mbar_t": 1164,
    "M_t": 5000,
    "G_t": 0,
    "alpha_t": 0,
    "Mpeak_t": 0,
    "gross_settled_t": 0,
    "v_t": null,
    "phi_t": 0,
    "delta_t": 1,
    "n_debtors": 1,
    "n_creditors": 2,
    "HHIplus_t": "0.5099254850556795503123486968",
    "notes": ""
  }
]