[
  {
    "day": 1,
    "S_t": 538,
    "Mbar_t": 538,
    "M_t": "26242.0000000000001",
    "G_t": 0,
    "alpha_t": 0,
    "Mpeak_t": 0,
    "gross_settled_t": 0,
    "v_t": null,
    "phi_t": 0,
    "delta_t": 1,
    "n_debtors": 1,
    "n_creditors": 2,
    "HHIplus_t": "0.8687138099252359696521606942",
    "notes": ""
  },
  {
    "day": 3,
    "S_t": 4593,
    "Mbar_t": 4593,
    "M_t": "26242.0000000000001",
    "G_t": 0,
    "alpha_t": 0,
    "Mpeak_t": 0,
    "gross_settled_t": 0,
    "v_t": null,
    "phi_t": 0,
    "delta_t": 1,
    "n_debtors": 1,
    "n_creditors": 2,
    "HHIplus_t": "0.8059789485500066862128773568",
    "notes": ""
  },
  {
    "day": 5,
    "S_t": 6635,
    "Mbar_t": 6635,
    "M_t": "26242.0000000000001",
    "G_t": 0,
    "alpha_t": 0,
    "Mpeak_t": 0,
    "gross_settled_t": 0,
    "v_t": null,
    "phi_t": 0,
    "delta_t": 1,
    "n_debtors": 1,
    "n_creditors": 2,
    "HHIplus_t": "0.8606417408084028373659585368",
    "notes": ""
  },
  {
    "day": 7,
    "S_t": 863,
    "Mbar_t": 863,
    "M_t": "26242.0000000000001",
    "G_t": 0,
    "alpha_t": 0,
    "Mpeak_t": 0,
    "gross_settled_t": 0,
    "v_t": null,
    "phi_t": 0,
    "delta_t": 1,
    "n_debtors": 1,
    "n_creditors": 2,
    "HHIplus_t": "0.5126005513118832819303703564",
    "notes": ""
  },
  {
    "day": 9,
    "S_t": 2367,
    "Mbar_t": 2367,
    "M_t": "26242.0000000000001",
    "G_t": 0,
    "alpha_t": 0,
    "Mpeak_t": 0,
    "gross_settled_t": 0,
    "v_t": null,
    "phi_t": 0,
    "delta_t": 1,
    "n_debtors": 1,
    "n_creditors": 2,
    "HHIplus_t": "0.6667671541290262586411631986",
    "notes": ""
  }
]