[
  {
    "day": 1,
    "S_t": 2693,
    "Mbar_t": 2693,
    "M_t": 15807,
    "G_t": 0,
    "alpha_t": 0,
    "Mpeak_t": 2693,
    "gross_settled_t": 2693,
    "v_t": 1,
    "phi_t": 1,
    "delta_t": 0,
    "n_debtors": 1,
    "n_creditors": 2,
    "HHIplus_t": "0.6976110445187417034357204228",
    "notes": ""
  },
  {
    "day": 2,
    "S_t": 3100,
    "Mbar_t": 3100,
    "M_t": 15807,
    "G_t": 0,
    "alpha_t": 0,
    "Mpeak_t": 0,
    "gross_settled_t": 0,
    "v_t": null,
    "phi_t": 0,
    "delta_t": 1,
    "n_debtors": 1,
    "n_creditors": 2,
    "HHIplus_t": "0.7294484911550468262226847034",
    "notes": ""
  },
  {
    "day": 8,
    "S_t": 6226,
    "Mbar_t": 6226,
    "M_t": 15807,
    "G_t": 0,
    "alpha_t": 0,
    "Mpeak_t": 0,
    "gross_settled_t": 0,
    "v_t": null,
    "phi_t": 0,
    "delta_t": 1,
    "n_debtors": 1,
    "n_creditors": 2,
    "HHIplus_t": "0.8522821047535030501707346444",
    "notes": ""
  },
  {
    "day": 9,
    "S_t": 657,
    "Mbar_t": 657,
    "M_t": 15807,
    "G_t": 0,
    "alpha_t": 0,
    "Mpeak_t": 0,
    "gross_settled_t": 0,
    "v_t": null,
    "phi_t": 0,
    "delta_t": 1,
    "n_debtors": 1,
    "n_creditors": 2,
    "HHIplus_t": "0.6362785503962710442975658462",
    "notes": ""
  },
  {
    "day": 10,
    "S_t": 2321,
    "Mbar_t": 2321,
    "M_t": 15807,
    "G_t": 0,
    "alpha_t": 0,
    "Mpeak_t": 0,
    "gross_settled_t": 0,
    "v_t": null,
    "phi_t": 0,
    "delta_t": 1,
    "n_debtors": 1,
    "n_creditors": 2,
    "HHIplus_t": "0.6619665601208529877533881772",
    "notes": ""
  }
]